atapi/__init__.py
atapi/__main__.py
atapi/comp/__init__.py
atapi/comp/algo.py
atapi-0.1.2.dist-info/LICENSE.txt
atapi-0.1.2.dist-info/METADATA
atapi-0.1.2.dist-info/WHEEL
atapi-0.1.2.dist-info/top_level.txt
atapi-0.1.2.dist-info/RECORD
