Metadata-Version: 2.1
Name: atapi
Version: 0.1.2
Summary: Algorithmic Trading Framework
Author-email: Miron Tewfik <miron@street.yoga>
License: The MIT License (MIT)        
Project-URL: homepage, https://street.yoga
Project-URL: documentation, https://github.com/streetyoga/atapi/wiki/Documentation
Project-URL: repository, https://github.com/streetyoga/atapi
Requires-Python: >=3.8
License-File: LICENSE.txt
Requires-Dist: pandas
Requires-Dist: binance-connector
Requires-Dist: scipy
Requires-Dist: requests
Provides-Extra: dev
Requires-Dist: flake8 ; extra == 'dev'
Requires-Dist: pytest ; extra == 'dev'
